{
  "hash": "304942b8fd827151f3c6edfda7e76b16",
  "result": {
    "engine": "knitr",
    "markdown": "---\ntitle: \"Tips\"\nlisting: \n  sort: \"date desc\"\n  type: grid\n  page-size: 9\n  categories: true\n  feed: true\n  contents: \"**/index.qmd\"\ncode-tools: false\ncomments: false\n---\n\n\n\n\n\n\n{{< iconify ic:outline-tips-and-updates >}} おすすめ記事\n\n\n\n\n::: {.cell}\n::: {.cell-output-display}\n\n```{=html}\n<div id=\"tips-carousel\" class=\"carousel carousel-dark slide\" data-bs-ride=\"carousel\">\n<div class=\"carousel-indicators\">\n<button type=\"button\" data-bs-target=\"#tips-carousel\" data-bs-slide-to=\"0\" aria-label=\"Slide 1\" class=\"active\" aria-current=\"true\"></button>\n<button type=\"button\" data-bs-target=\"#tips-carousel\" data-bs-slide-to=\"1\" aria-label=\"Slide 2\"></button>\n<button type=\"button\" data-bs-target=\"#tips-carousel\" data-bs-slide-to=\"2\" aria-label=\"Slide 3\"></button>\n</div>\n<div class=\"carousel-inner\">\n<div class=\"carousel-item active\" data-bs-interval=\"5000\">\n<a href=\"240504_container/index.html\">\n<img src=\"240504_container/image/docker-desktop.png\" class=\"d-block  mx-auto border\"/>\n</a>\n<div class=\"carousel-caption d-none d-md-block\">\n<p class=\"fw-light\">開発コンテナを使って R 環境を構築！</p>\n</div>\n</div>\n<div class=\"carousel-item\" data-bs-interval=\"5000\">\n<a href=\"240629_write_thesis/index.html\">\n<img src=\"240629_write_thesis/image/create_document.png\" class=\"d-block  mx-auto border\"/>\n</a>\n<div class=\"carousel-caption d-none d-md-block\">\n<p class=\"fw-light\">【PDF】Quarto で論文を書く</p>\n</div>\n</div>\n<div class=\"carousel-item\" data-bs-interval=\"5000\">\n<a href=\"240329_rmarkdown_pdf/index.html\">\n<img src=\"240329_rmarkdown_pdf/image/plot_cars.png\" class=\"d-block  mx-auto border\"/>\n</a>\n<div class=\"carousel-caption d-none d-md-block\">\n<p class=\"fw-light\">Quarto &amp; R MarkdownでPDF出力【LaTeX】</p>\n</div>\n</div>\n</div>\n<button class=\"carousel-control-prev\" type=\"button\" data-bs-target=\"#tips-carousel\" data-bs-slide=\"prev\">\n<span class=\"carousel-control-prev-icon\" aria-hidden=\"true\"></span>\n<span class=\"visually-hidden\">Prevoius</span>\n</button>\n<button class=\"carousel-control-next\" type=\"button\" data-bs-target=\"#tips-carousel\" data-bs-slide=\"next\">\n<span class=\"carousel-control-next-icon\" aria-hidden=\"true\"></span>\n<span class=\"visually-hidden\">Next</span>\n</button>\n</div>\n```\n\n:::\n:::\n\n\n\n\n::: {.callout-note}\n## 開発環境\n\n最終更新日：2024年07月26日\n\n- Ubuntu 22.04\n\n- RStudio 2024.04.2+764 (Chocolate Cosmos) for Ubuntu Jammy\n\n- R version 4.4.1 (2024-06-14)\n\n- Python 3.10.12\n\n- julia version 1.10.4\n\n- Quarto 1.5.55\n:::",
    "supporting": [],
    "filters": [
      "rmarkdown/pagebreak.lua"
    ],
    "includes": {},
    "engineDependencies": {},
    "preserve": {},
    "postProcess": true
  }
}